<?xml version="1.0" ?>
<annotation>
  <folder>2020_06/ims</folder>
  <filename>2092.18_283.JPG</filename>
  <path>2020_06/ims/2092.18_283.JPG</path>
  <source>
    <database>Unknown</database>
  </source>
  <size>
    <width>3008</width>
    <height>2000</height>
    <depth>3</depth>
  </size>
  <segmented>0</segmented>
  <rotation>0</rotation>
  <adjust>
    <brightness>1.0</brightness>
  </adjust>
  <object>
    <name>sheepface</name>
    <pose>Unspecified</pose>
    <truncated>0</truncated>
    <difficult>0</difficult>
    <bndbox>
      <xmin>811</xmin>
      <ymin>114</ymin>
      <xmax>2139</xmax>
      <ymax>1383</ymax>
    </bndbox>
    <subobj>
      <name>reye</name>
      <coords>
        <x1>1127</x1>
        <y1>433</y1>
        <x2>1244</x2>
        <y2>535</y2>
      </coords>
    </subobj>
    <subobj>
      <name>rmouth</name>
      <coords>
        <x1>1691</x1>
        <y1>1003</y1>
        <x2>2001</x2>
        <y2>1018</y2>
      </coords>
    </subobj>
    <subobj>
      <name>rnostril</name>
      <coords>
        <x1>1808</x1>
        <y1>813</y1>
        <x2>1993</x2>
        <y2>868</y2>
      </coords>
    </subobj>
  </object>
</annotation>