<?xml version="1.0" ?>
<annotation>
  <folder>2020_06/ims</folder>
  <filename>2415.16_529.JPG</filename>
  <path>2020_06/ims/2415.16_529.JPG</path>
  <source>
    <database>Unknown</database>
  </source>
  <size>
    <width>3008</width>
    <height>2000</height>
    <depth>3</depth>
  </size>
  <segmented>0</segmented>
  <rotation>0</rotation>
  <adjust>
    <brightness>1.8</brightness>
    <contrast>0.6</contrast>
  </adjust>
  <object>
    <name>sheepface</name>
    <pose>Unspecified</pose>
    <truncated>0</truncated>
    <difficult>0</difficult>
    <bndbox>
      <xmin>992</xmin>
      <ymin>140</ymin>
      <xmax>2236</xmax>
      <ymax>1401</ymax>
    </bndbox>
    <subobj>
      <name>leye</name>
      <coords>
        <x1>1680</x1>
        <y1>500</y1>
        <x2>1805</x2>
        <y2>596</y2>
      </coords>
    </subobj>
    <subobj>
      <name>lmouth</name>
      <coords>
        <x1>1308</x1>
        <y1>1289</y1>
        <x2>1501</x2>
        <y2>1146</y2>
      </coords>
    </subobj>
    <subobj>
      <name>lnostril</name>
      <coords>
        <x1>1229</x1>
        <y1>1173</y1>
        <x2>1311</x2>
        <y2>1061</y2>
      </coords>
    </subobj>
  </object>
</annotation>