<?xml version="1.0" ?>
<annotation>
  <folder>2020_06/ims</folder>
  <filename>2773.16_419.JPG</filename>
  <path>2020_06/ims/2773.16_419.JPG</path>
  <source>
    <database>Unknown</database>
  </source>
  <size>
    <width>3008</width>
    <height>2000</height>
    <depth>3</depth>
  </size>
  <segmented>0</segmented>
  <rotation>0</rotation>
  <object>
    <name>sheepface</name>
    <pose>Unspecified</pose>
    <truncated>0</truncated>
    <difficult>0</difficult>
    <bndbox>
      <xmin>1334</xmin>
      <ymin>488</ymin>
      <xmax>2944</xmax>
      <ymax>1997</ymax>
    </bndbox>
  </object>
</annotation>