<?xml version="1.0" ?>
<annotation>
  <folder>2020_06/ims</folder>
  <filename>454.18_219.JPG</filename>
  <path>2020_06/ims/454.18_219.JPG</path>
  <source>
    <database>Unknown</database>
  </source>
  <size>
    <width>3008</width>
    <height>2000</height>
    <depth>3</depth>
  </size>
  <segmented>0</segmented>
  <rotation>0</rotation>
  <adjust>
    <brightness>1.8</brightness>
  </adjust>
  <object>
    <name>sheepface</name>
    <pose>Unspecified</pose>
    <truncated>0</truncated>
    <difficult>0</difficult>
    <bndbox>
      <xmin>269</xmin>
      <ymin>15</ymin>
      <xmax>2139</xmax>
      <ymax>1763</ymax>
    </bndbox>
    <subobj>
      <name>reye</name>
      <coords>
        <x1>623</x1>
        <y1>459</y1>
        <x2>720</x2>
        <y2>573</y2>
      </coords>
    </subobj>
    <subobj>
      <name>leye</name>
      <coords>
        <x1>1513</x1>
        <y1>439</y1>
        <x2>1595</x2>
        <y2>564</y2>
      </coords>
    </subobj>
    <subobj>
      <name>rnostril</name>
      <coords>
        <x1>922</x1>
        <y1>1520</y1>
        <x2>1074</x2>
        <y2>1675</y2>
      </coords>
    </subobj>
    <subobj>
      <name>lnostril</name>
      <coords>
        <x1>1118</x1>
        <y1>1673</y1>
        <x2>1267</x2>
        <y2>1529</y2>
      </coords>
    </subobj>
  </object>
</annotation>