<?xml version="1.0" ?>
<annotation>
  <folder>2019_12/Ewes/105_PANA</folder>
  <filename>P1050032.JPG</filename>
  <path>2019_12/Ewes/105_PANA/P1050032.JPG</path>
  <source>
    <database>Unknown</database>
  </source>
  <size>
    <width>4592</width>
    <height>2584</height>
    <depth>3</depth>
  </size>
  <segmented>0</segmented>
  <rotation>0</rotation>
  <adjust>
    <brightness>1.0</brightness>
  </adjust>
  <object>
    <name>sheepface</name>
    <pose>Unspecified</pose>
    <truncated>0</truncated>
    <difficult>0</difficult>
    <bndbox>
      <xmin>1595</xmin>
      <ymin>925</ymin>
      <xmax>3292</xmax>
      <ymax>2544</ymax>
    </bndbox>
    <subobj>
      <name>reye</name>
      <coords>
        <x1>1934</x1>
        <y1>1422</y1>
        <x2>2028</x2>
        <y2>1524</y2>
      </coords>
    </subobj>
    <subobj>
      <name>leye</name>
      <coords>
        <x1>2622</x1>
        <y1>1274</y1>
        <x2>2720</x2>
        <y2>1408</y2>
      </coords>
    </subobj>
    <subobj>
      <name>rmouth</name>
      <coords>
        <x1>2336</x1>
        <y1>2369</y1>
        <x2>2417</x2>
        <y2>2352</y2>
      </coords>
    </subobj>
    <subobj>
      <name>lmouth</name>
      <coords>
        <x1>2439</x1>
        <y1>2347</y1>
        <x2>2546</x2>
        <y2>2311</y2>
      </coords>
    </subobj>
    <subobj>
      <name>rnostril</name>
      <coords>
        <x1>2225</x1>
        <y1>2191</y1>
        <x2>2367</x2>
        <y2>2289</y2>
      </coords>
    </subobj>
    <subobj>
      <name>lnostril</name>
      <coords>
        <x1>2403</x1>
        <y1>2271</y1>
        <x2>2510</x2>
        <y2>2128</y2>
      </coords>
    </subobj>
  </object>
  <object>
    <name>sheepface2</name>
    <bndbox>
      <xmin>822</xmin>
      <ymin>460</ymin>
      <xmax>1608</xmax>
      <ymax>1395</ymax>
    </bndbox>
    <subobj>
      <name>reye</name>
      <coords>
        <x1>902</x1>
        <y1>657</y1>
        <x2>1005</x2>
        <y2>756</y2>
      </coords>
    </subobj>
    <subobj>
      <name>leye</name>
      <coords>
        <x1>1438</x1>
        <y1>599</y1>
        <x2>1505</x2>
        <y2>688</y2>
      </coords>
    </subobj>
    <subobj>
      <name>rmouth</name>
      <coords>
        <x1>1260</x1>
        <y1>1337</y1>
        <x2>1353</x2>
        <y2>1332</y2>
      </coords>
    </subobj>
    <subobj>
      <name>lmouth</name>
      <coords>
        <x1>1371</x1>
        <y1>1332</y1>
        <x2>1447</x2>
        <y2>1310</y2>
      </coords>
    </subobj>
    <subobj>
      <name>rnostril</name>
      <coords>
        <x1>1197</x1>
        <y1>1176</y1>
        <x2>1340</x2>
        <y2>1256</y2>
      </coords>
    </subobj>
    <subobj>
      <name>lnostril</name>
      <coords>
        <x1>1367</x1>
        <y1>1252</y1>
        <x2>1447</x2>
        <y2>1162</y2>
      </coords>
    </subobj>
  </object>
</annotation>